weml_validator/__init__.py
weml_validator/__main__.py
weml_validator/attribute_validators.py
weml_validator/errors.py
weml_validator/repository.py
weml_validator/tag_validators.py
weml_validator/validators.py
weml_validator-0.2.0.dist-info/METADATA
weml_validator-0.2.0.dist-info/WHEEL
weml_validator-0.2.0.dist-info/RECORD
