Metadata-Version: 2.1
Name: weml-validator
Version: 0.2.0
Summary: Validator for the WEML document format by EGW Writings
Author: Kyrylo Kobets
Author-email: mjr@itage.biz
Requires-Python: >=3.12,<4.0
Classifier: Programming Language :: Python :: 3
Classifier: Programming Language :: Python :: 3.12
Requires-Dist: bs4 (>=0.0.2,<0.0.3)
